mputil/__init__.py
mputil/map.py
mputil-0.1.1.data/data/CHANGELOG.md
mputil-0.1.1.data/data/LICENSE.txt
mputil-0.1.1.dist-info/METADATA
mputil-0.1.1.dist-info/RECORD
mputil-0.1.1.dist-info/WHEEL
mputil-0.1.1.dist-info/top_level.txt
mputil-0.1.1.dist-info/zip-safe
