Metadata-Version: 2.1
Name: mputil
Version: 0.1.1
Summary: Utility functions for Python's multiprocessing module
Home-page: https://github.com/rasbt/mputil
Author: Sebastian Raschka
Author-email: mail@sebastianraschka.com
License: MIT
Keywords: multiprocessing
Platform: any
Classifier: License :: OSI Approved :: MIT License
Classifier: Development Status :: 5 - Production/Stable
Classifier: Operating System :: Microsoft :: Windows
Classifier: Operating System :: POSIX
Classifier: Operating System :: Unix
Classifier: Operating System :: MacOS
Classifier: Programming Language :: Python :: 3.6
Classifier: Topic :: Scientific/Engineering
